featurefuse/__init__.py
featurefuse/base.py
featurefuse/generator.py
featurefuse-0.1.2.dist-info/METADATA
featurefuse-0.1.2.dist-info/WHEEL
featurefuse-0.1.2.dist-info/licenses/LICENSE
featurefuse-0.1.2.dist-info/RECORD
