Metadata-Version: 2.1
Name: featurefuse
Version: 0.1.2
Summary: featurefuse is Python package that allows you to choose which feature you make for machine learning models using yaml configuration.
Author-email: "yutaro.ueno" <yutarofortech@gmail.com>
License-Expression: MIT
License-File: LICENSE
Requires-Python: >=3.8
Requires-Dist: pandas~=2.0.2
